{
  "meta": {}, 
  "date_of_occurrence": "2006-07-03", 
  "original_url": "http://www.maib.gov.uk/publications/completed_preliminary_examinations/completed_preliminary_examinations_2006/completed_pe_summary___ocean_harvest_ii.cfm", 
  "_assets": [], 
  "title": "Completed PE Summary - Ocean Harvest II", 
  "raw_html": "<div id=\"mainContentArea\" style=\"width: 545px;\"><div id=\"pageTitleContainer\">\r\n<p>\r\n</p>\r\n</div>\r\n<div id=\"TextContainer\">&#160;\r\r\n\r\r\n<table border=\"1\" width=\"100%\" cellpadding=\"1\" cellspacing=\"2\">\r\r\n\r\r\n\r\r\n<tr>\r\r\n<td valign=\"top\">Category</td>\r\r\n\t<td valign=\"top\">Fishing</td>\r\r\n</tr>\r\r\n\r\r\n\r\r\n<tr>\r\r\n<td valign=\"top\">Registered Owner &amp; Manager:</td>\r\r\n\t<td valign=\"top\">Mr C Campbell</td>\r\r\n</tr>\r\r\n\r\r\n\r\r\n<tr>\r\r\n<td valign=\"top\">Port of registry:</td>\r\r\n\t<td valign=\"top\">Newry</td>\r\r\n</tr>\r\r\n\r\r\n\r\r\n<tr>\r\r\n<td valign=\"top\">Flag:</td>\r\r\n\t<td valign=\"top\">UK</td>\r\r\n</tr>\r\r\n\r\r\n\r\r\n<tr>\r\r\n<td valign=\"top\">Type:</td>\r\r\n\t<td valign=\"top\">Fish Catching</td>\r\r\n</tr>\r\r\n\r\r\n\r\r\n<tr>\r\r\n<td valign=\"top\">Built:</td>\r\r\n\t<td valign=\"top\">1972</td>\r\r\n</tr>\r\r\n\r\r\n<tr>\r\r\n<td valign=\"top\">Construction:</td>\r\r\n\t<td valign=\"top\">Wood</td>\r\r\n</tr>\r\r\n\r\r\n\r\r\n<tr>\r\r\n<td valign=\"top\">Length overall:</td>\r\r\n\t<td valign=\"top\">20.66</td>\r\r\n</tr>\r\r\n\r\r\n\r\r\n<tr>\r\r\n<td valign=\"top\">Gross tonnage:</td>\r\r\n\t<td valign=\"top\">96.00</td>\r\r\n</tr>\r\r\n\r\r\n\r\r\n<tr>\r\r\n<td valign=\"top\">Date &amp; Time</td>\r\r\n\t<td valign=\"top\">07/03/06 12:13</td>\r\r\n</tr>\r\r\n\r\r\n\r\r\n<tr>\r\r\n<td valign=\"top\">Location of incident:</td>\r\r\n\t<td valign=\"top\">Foriegn waters 5345.8N 00528.8W</td>\r\r\n</tr>\r\r\n\r\r\n\r\r\n<tr>\r\r\n<td valign=\"top\">Incident Type:</td>\r\r\n\t<td valign=\"top\">Fire/Explosion</td>\r\r\n</tr>\r\r\n\r\r\n\r\r\n<tr>\r\r\n<td valign=\"top\">Persons onboard:</td>\r\r\n\t<td valign=\"top\">5 crew</td>\r\r\n</tr>\r\r\n\r\r\n\r\r\n<tr>\r\r\n<td valign=\"top\">Injuries/ fatalities:</td>\r\r\n\t<td valign=\"top\">None</td>\r\r\n</tr>\r\r\n\r\r\n\r\r\n<tr>\r\r\n<td valign=\"top\">Damage/ Pollution:</td>\r\r\n\t<td valign=\"top\">Ship lost/No Pollution</td>\r\r\n</tr>\r\r\n\r\r\n</table>\r\r\n\r\r\n<p>\r\r\n</p>\r\r\n\r\r\n<p><span>Synopsis</span></p>\r\r\n\r\r\n<p>The 20 meter wooden hulled fishing vessel Ocean Harvest II was trawling approximately 25 miles off its home port of Kilkeel in Northern Ireland when at 1200 UTC the skipper smelt smoke. He immediately investigated and discovered smoke but no flames, in the mess room and then high up in the engine space and he alerted the four sleeping ememebers.\r\r\n</p>\r\r\n\r\r\n<p>Within seconds the fire took hold and the skipper and crew only just had time to broadcast a hurried distress call and abandon the vessel.\r\r\n\r\r\n</p>\r\r\n<p>The five men were rescued by helicopter after 45 minutes in the life raft. The vessel continued to burn until she sank at 1655 UTC.</p>\r\r\n\r\r\n\r\r\n\r\r\n\r\r\n<p><span>Action taken:</span></p>\r\r\n\r\r\n<p>The Chief Inspector has written to the vessel's owners commenting on the efficiency of the crew's abandonment from the vessel. He also gave strong advice concerning regularly testing the insulation of electric cabling on board their vessels and ensuring that all their crews undertake the statutory safety training.\r\r\n</p>\r\r\n\r\r\n<p>The Chief Inspector has also written to the MCA recommending that it:\r\r\n\r\r\n</p>\r\r\n\r\r\n<ul>\r\r\n<li>\r\r\n\t<p>reminds the fishing industry of the requirement to ensure that all new entrants complete safety and survival training and, in this respect, that courses should be provided that are suitable for those that do not have English as their first language. \r\r\n</p>\r\r\n</li>\r\r\n\r\r\n<li>\r\r\n\t<p>requires the regular testing of electrical insulation on fishing vessels. \r\r\n</p>\r\r\n</li>\r\r\n\r\r\n\r\r\n</ul>\r\r\n\r\r\n<hr></div>\r\n</div>", 
  "summary": "", 
  "report_type": "completed-preliminary-examination", 
  "vessel_type": [
    "fishing-vessel"
  ], 
  "body": "\u00a0\n\nCategory |   | Fishing | \nRegistered Owner & Manager: |   | Mr C Campbell | \nPort of registry: |   | Newry | \nFlag: |   | UK | \nType: |   | Fish Catching | \nBuilt: |   | 1972 | \nConstruction: |   | Wood | \nLength overall: |   | 20.66 | \nGross tonnage: |   | 96.00 | \nDate & Time |   | 07/03/06 12:13 | \nLocation of incident: |   | Foriegn waters 5345.8N 00528.8W | \nIncident Type: |   | Fire/Explosion | \nPersons onboard: |   | 5 crew | \nInjuries/ fatalities: |   | None | \nDamage/ Pollution: |   | Ship lost/No Pollution | \n\nSynopsis\n\nThe 20 meter wooden hulled fishing vessel Ocean Harvest II was trawling approximately 25 miles off its home port of Kilkeel in Northern Ireland when at 1200 UTC the skipper smelt smoke. He immediately investigated and discovered smoke but no flames, in the mess room and then high up in the engine space and he alerted the four sleeping ememebers. \n\nWithin seconds the fire took hold and the skipper and crew only just had time to broadcast a hurried distress call and abandon the vessel. \n\nThe five men were rescued by helicopter after 45 minutes in the life raft. The vessel continued to burn until she sank at 1655 UTC.\n\nAction taken:\n\nThe Chief Inspector has written to the vessel's owners commenting on the efficiency of the crew's abandonment from the vessel. He also gave strong advice concerning regularly testing the insulation of electric cabling on board their vessels and ensuring that all their crews undertake the statutory safety training. \n\nThe Chief Inspector has also written to the MCA recommending that it: \n\n  * reminds the fishing industry of the requirement to ensure that all new entrants complete safety and survival training and, in this respect, that courses should be provided that are suitable for those that do not have English as their first language. \n\n  * requires the regular testing of electrical insulation on fishing vessels. \n\n* * *\n"
}