{
  "meta": {}, 
  "date_of_occurrence": "2007-03-04", 
  "original_url": "http://www.maib.gov.uk/publications/completed_preliminary_examinations/completed_preliminary_examinations_2007/retainer.cfm", 
  "_assets": [], 
  "title": "Completed PE Summary - Retainer", 
  "raw_html": "<div id=\"mainContentArea\" style=\"width: 545px;\"><div id=\"pageTitleContainer\">\r\n<p>\r\n</p>\r\n</div>\r\n<div id=\"pageTitleContainer\">\r\n<p>\r\n</p>\r\n</div>\r\n<div id=\"TextContainer\"><table border=\"1\" width=\"100%\" cellpadding=\"1\" cellspacing=\"2\">\r\r\n\r\r\n\r\r\n<tr>\r\r\n<td valign=\"top\">Category</td>\r\r\n\t<td valign=\"top\">Merchant</td>\r\r\n</tr>\r\r\n\r\r\n\r\r\n\r\r\n<tr>\r\r\n<td valign=\"top\">Port of registry:</td>\r\r\n\t<td valign=\"top\">London</td>\r\r\n</tr>\r\r\n\r\r\n\r\r\n<tr>\r\r\n<td valign=\"top\">Flag:</td>\r\r\n\t<td valign=\"top\">United Kingdom</td>\r\r\n</tr>\r\r\n\r\r\n\r\r\n<tr>\r\r\n<td valign=\"top\">Type:</td>\r\r\n\t<td valign=\"top\">Tug</td>\r\r\n</tr>\r\r\n\r\r\n\r\r\n<tr>\r\r\n<td valign=\"top\">Built:</td>\r\r\n\t<td valign=\"top\">1979</td>\r\r\n</tr>\r\r\n\r\r\n\r\r\n\r\r\n\r\r\n<tr>\r\r\n<td valign=\"top\">Construction:</td>\r\r\n\t<td valign=\"top\">Steel</td>\r\r\n</tr>\r\r\n\r\r\n\r\r\n<tr>\r\r\n<td valign=\"top\">Length overall:</td>\r\r\n\t<td valign=\"top\">23.55 metres</td>\r\r\n</tr>\r\r\n\r\r\n\r\r\n<tr>\r\r\n<td valign=\"top\">Gross tonnage:</td>\r\r\n\t<td valign=\"top\">119</td>\r\r\n</tr>\r\r\n\r\r\n\r\r\n<tr>\r\r\n<td valign=\"top\">Date &amp; Time</td>\r\r\n\t<td valign=\"top\">03/04/07 19:27</td>\r\r\n</tr>\r\r\n\r\r\n\r\r\n<tr>\r\r\n<td valign=\"top\">Location of incident:</td>\r\r\n\t<td valign=\"top\">Mucking Barge Roads</td>\r\r\n</tr>\r\r\n\r\r\n\r\r\n<tr>\r\r\n<td valign=\"top\">Incident Type:</td>\r\r\n\t<td valign=\"top\">Accident to Person</td>\r\r\n</tr>\r\r\n\r\r\n\r\r\n\r\r\n\r\r\n<tr>\r\r\n<td valign=\"top\">Injuries/ fatalities:</td>\r\r\n\t<td valign=\"top\">1</td>\r\r\n</tr>\r\r\n\r\r\n\r\r\n<tr>\r\r\n<td valign=\"top\">Damage/ Pollution:</td>\r\r\n\t<td valign=\"top\">Nil</td>\r\r\n</tr>\r\r\n\r\r\n</table>\r\r\n\r\r\n<p>\r\r\n</p>\r\r\n\r\r\n<p><span>Synopsis</span></p>\r\r\n\r\r\n<p>Retainer was employed exclusively to tow barges of containerised rubbish out of London along the Thames.  The accident occurred on the last barge movement of the day, during an approach to the moorings at Mucking Barge Roads.  On the approach, the tug skipper backed up to the barges and three lightermen transferred from the tug to the towed barges in preparation for coming alongside the barge mooring.  There were four barges under tow, three abreast, with one barge behind.  The 2 tow ropes, that were being used to tow the barges, were shortened up on the barge bitts, one to the centre barge, the other to the starboard barge.  Another crewman remained on the aft deck of the tug to tend the tow ropes as required.  As the weight returned to the tow ropes everything appeared normal, with the slow turn towards the mooring shaping well and the line of the tow ropes appearing fine.  There was then a loud noise and a shout from the crewman on the aft deck as he was hit in the chest by one of the tow ropes.  Tragically, the injuries sustained were fatal.</p>\r\r\n\r\r\n<p>None of the crew on Retainer saw what happened.  Both tow ropes were intact after the incident.  The most likely cause of the accident was due to one of the tow ropes becoming snagged on the forward section of the barge.  When the snag cleared, it transmitted a wave along the tow rope which caught the crewman in the chest with significant force.</p>\r\r\n\r\r\n\r\r\n\r\r\n<p><span>Action taken:</span></p>\r\r\n\r\r\n<p>Recommendations have been made to the tug managers regarding the hazards of working near lines under load, the need for guidance on crew roles and responsibilities, and reviewing communication methods employed by tug and barge crews.</p>\r\r\n\r\r\n\r\r\n\r\r\n\r\r\n<hr></div>\r\n</div>", 
  "summary": "", 
  "report_type": "completed-preliminary-examination", 
  "vessel_type": [
    "merchant-vessel-100-gross-tons-or-over"
  ], 
  "body": "Category |   | Merchant | \nPort of registry: |   | London | \nFlag: |   | United Kingdom | \nType: |   | Tug | \nBuilt: |   | 1979 | \nConstruction: |   | Steel | \nLength overall: |   | 23.55 metres | \nGross tonnage: |   | 119 | \nDate & Time |   | 03/04/07 19:27 | \nLocation of incident: |   | Mucking Barge Roads | \nIncident Type: |   | Accident to Person | \nInjuries/ fatalities: |   | 1 | \nDamage/ Pollution: |   | Nil | \n\nSynopsis\n\nRetainer was employed exclusively to tow barges of containerised rubbish out of London along the Thames. The accident occurred on the last barge movement of the day, during an approach to the moorings at Mucking Barge Roads. On the approach, the tug skipper backed up to the barges and three lightermen transferred from the tug to the towed barges in preparation for coming alongside the barge mooring. There were four barges under tow, three abreast, with one barge behind. The 2 tow ropes, that were being used to tow the barges, were shortened up on the barge bitts, one to the centre barge, the other to the starboard barge. Another crewman remained on the aft deck of the tug to tend the tow ropes as required. As the weight returned to the tow ropes everything appeared normal, with the slow turn towards the mooring shaping well and the line of the tow ropes appearing fine. There was then a loud noise and a shout from the crewman on the aft deck as he was hit in the chest by one of the tow ropes. Tragically, the injuries sustained were fatal.\n\nNone of the crew on Retainer saw what happened. Both tow ropes were intact after the incident. The most likely cause of the accident was due to one of the tow ropes becoming snagged on the forward section of the barge. When the snag cleared, it transmitted a wave along the tow rope which caught the crewman in the chest with significant force.\n\nAction taken:\n\nRecommendations have been made to the tug managers regarding the hazards of working near lines under load, the need for guidance on crew roles and responsibilities, and reviewing communication methods employed by tug and barge crews.\n\n* * *\n"
}